fglib/__init__.py
fglib/edges.py
fglib/graphs.py
fglib/inference.py
fglib/nodes.py
fglib/rv.py
fglib/utils.py
fglib/tests/__init__.py
fglib/tests/test_edges.py
fglib/tests/test_graphs.py
fglib/tests/test_inference.py
fglib/tests/test_nodes.py
fglib/tests/test_rv.py
fglib/tests/test_utils.py
fglib-0.2.3.dist-info/DESCRIPTION.rst
fglib-0.2.3.dist-info/METADATA
fglib-0.2.3.dist-info/RECORD
fglib-0.2.3.dist-info/WHEEL
fglib-0.2.3.dist-info/metadata.json
fglib-0.2.3.dist-info/top_level.txt
